{
  "defi-milestone-cron-operations": {
    "archived_at": null,
    "created_at": "2026-05-02T10:23:21.033981+00:00",
    "last_patched_at": "2026-05-02T10:23:38.759990+00:00",
    "last_used_at": "2026-05-02T10:23:24.289245+00:00",
    "last_viewed_at": "2026-05-02T10:23:24.287729+00:00",
    "patch_count": 4,
    "pinned": false,
    "state": "active",
    "use_count": 1,
    "view_count": 1
  },
  "hackathon-prep": {
    "archived_at": null,
    "created_at": "2026-05-02T09:16:39.702853+00:00",
    "last_patched_at": null,
    "last_used_at": "2026-05-02T09:16:39.704355+00:00",
    "last_viewed_at": "2026-05-02T09:16:39.702867+00:00",
    "patch_count": 0,
    "pinned": false,
    "state": "active",
    "use_count": 1,
    "view_count": 1
  },
  "hackathon-prep-audit": {
    "archived_at": null,
    "created_at": "2026-05-01T12:22:08.446776+00:00",
    "last_patched_at": "2026-05-01T12:22:08.446789+00:00",
    "last_used_at": null,
    "last_viewed_at": null,
    "patch_count": 1,
    "pinned": false,
    "state": "active",
    "use_count": 0,
    "view_count": 0
  },
  "hermes-operations": {
    "archived_at": null,
    "created_at": "2026-05-01T17:17:48.187835+00:00",
    "last_patched_at": "2026-05-02T06:13:02.812533+00:00",
    "last_used_at": "2026-05-02T10:49:13.567402+00:00",
    "last_viewed_at": "2026-05-02T10:49:13.566070+00:00",
    "patch_count": 6,
    "pinned": false,
    "state": "active",
    "use_count": 6,
    "view_count": 6
  },
  "kanban-labs": {
    "archived_at": null,
    "created_at": "2026-05-01T12:23:55.290857+00:00",
    "last_patched_at": "2026-05-01T12:23:55.290866+00:00",
    "last_used_at": null,
    "last_viewed_at": null,
    "patch_count": 1,
    "pinned": false,
    "state": "active",
    "use_count": 0,
    "view_count": 0
  },
  "security-contest-monitoring": {
    "archived_at": null,
    "created_at": "2026-05-02T09:17:22.143787+00:00",
    "last_patched_at": "2026-05-02T10:36:21.507914+00:00",
    "last_used_at": "2026-05-02T10:35:11.242276+00:00",
    "last_viewed_at": "2026-05-02T10:35:11.241000+00:00",
    "patch_count": 8,
    "pinned": false,
    "state": "active",
    "use_count": 2,
    "view_count": 2
  }
}