{
  "lastUpdated": "2026-06-16T13:22:34.747Z",
  "pool": "AVAX/USDC",
  "chain": "Avalanche",
  "dex": "LFJ",
  "currentPrice": 6.9,
  "priceChange24h": -1.19,
  "volume24h": 1393061.59,
  "liquidity": 378209.23,
  "lpPosition": {
    "pair": "AVAX/USDC",
    "feeTier": "10bps",
    "shape": "bid-ask",
    "currentPrice": 6.9,
    "rangeMin": 6.78,
    "rangeMax": 7.02,
    "avaxAmount": 5.777333,
    "usdcAmount": 6.338868,
    "totalValue": 46.2,
    "totalValueUSD": 46.2,
    "activeBin": 8362895,
    "binStep": 10,
    "totalBins": 30
  },
  "fees": {
    "dailyFees": 0.16,
    "cumulativeFees": 0.16,
    "feeCurrency": "USD"
  },
  "efficiency": 65,
  "hero": {
    "positionUsd": 46.2,
    "dailyFees": 0.16,
    "efficiency": 65,
    "efficiencyZone": "Inner",
    "shape": "Bid-Ask",
    "rangeStatus": "In Range",
    "currentPrice": 6.9,
    "rangeMin": 6.78,
    "rangeMax": 7.02,
    "milestoneNext": "Raider",
    "milestoneTarget": 55,
    "milestoneProgress": 84
  },
  "marketIntel": {
    "avaxPrice": 6.9,
    "change24h": -1.19,
    "volume24h": 1393061.59,
    "tvl": 378209.23
  },
  "strategyAdvisor": {
    "efficiency": 65,
    "efficiencyZone": "Inner",
    "recommendedAction": "Hold",
    "dcaType": "Moderate DCA",
    "shape": "Bid-Ask"
  },
  "milestones": {
    "Scout": 5,
    "Raider": 20,
    "Warlord": 55,
    "Fisher": 100,
    "Sovereign": 200
  },
  "feeMilestones": {
    "currentDailyFees": 0.16,
    "cumulativeFees": 0.16,
    "nextMilestone": "Raider",
    "nextTarget": 55,
    "progress": 84
  },
  "curveData": {
    "currentPrice": 6.9,
    "rangeMin": 6.78,
    "rangeMax": 7.02,
    "bins": [
      {
        "price": 6.78,
        "depth": 0.046630019367356466
      },
      {
        "price": 6.7883,
        "depth": 0.0685541027360766
      },
      {
        "price": 6.7966,
        "depth": 0.0968596490755249
      },
      {
        "price": 6.8048,
        "depth": 0.1353863396122498
      },
      {
        "price": 6.8131,
        "depth": 0.18253265163804833
      },
      {
        "price": 6.8214,
        "depth": 0.24086698925672595
      },
      {
        "price": 6.8297,
        "depth": 0.31001228143640724
      },
      {
        "price": 6.8379,
        "depth": 0.3891065679613025
      },
      {
        "price": 6.8462,
        "depth": 0.4757030140663568
      },
      {
        "price": 6.8545,
        "depth": 0.5670308745832752
      },
      {
        "price": 6.8628,
        "depth": 0.6524957862920974
      },
      {
        "price": 6.871,
        "depth": 0.7433855329480688
      },
      {
        "price": 6.8793,
        "depth": 0.8123262028498052
      },
      {
        "price": 6.8876,
        "depth": 0.8745749303607654
      },
      {
        "price": 6.8959,
        "depth": 0.9029112726345766
      },
      {
        "price": 6.9041,
        "depth": 0.9658203035367634
      },
      {
        "price": 6.9124,
        "depth": 1
      },
      {
        "price": 6.9207,
        "depth": 0.9584105257415918
      },
      {
        "price": 6.929,
        "depth": 0.89287071640354
      },
      {
        "price": 6.9372,
        "depth": 0.801622657392832
      },
      {
        "price": 6.9455,
        "depth": 0.6988912131787447
      },
      {
        "price": 6.9538,
        "depth": 0.5931715238203837
      },
      {
        "price": 6.9621,
        "depth": 0.4830147129391678
      },
      {
        "price": 6.9703,
        "depth": 0.3901339179427292
      },
      {
        "price": 6.9786,
        "depth": 0.299275101929649
      },
      {
        "price": 6.9869,
        "depth": 0.22202451398951495
      },
      {
        "price": 6.9952,
        "depth": 0.16158519216490153
      },
      {
        "price": 7.0034,
        "depth": 0.11364412455847053
      },
      {
        "price": 7.0117,
        "depth": 0.07732190993336165
      },
      {
        "price": 7.02,
        "depth": 0.05162446344648359
      }
    ]
  },
  "walletBalances": {
    "avax": 0.0976285420647475,
    "wavax": 6.06671055027e-7,
    "usdc": 0.000009,
    "liquidUsd": 0.67
  }
}