{
  "lastUpdated": "2026-06-17T20:21:06.371Z",
  "pool": "AVAX/USDC",
  "chain": "Avalanche",
  "dex": "LFJ",
  "currentPrice": 6.74,
  "priceChange24h": -2.08,
  "volume24h": 1902892.54,
  "liquidity": 373612.89,
  "lpPosition": {
    "pair": "AVAX/USDC",
    "feeTier": "10bps",
    "shape": "bid-ask",
    "displayShape": "Bid-Ask",
    "currentPrice": 6.74,
    "rangeMin": 6.6518,
    "rangeMax": 6.9162,
    "avaxAmount": 3.248339,
    "usdcAmount": 24.314331,
    "totalValue": 46.21,
    "totalValueUSD": 46.21,
    "activeBin": 8362874,
    "binStep": 10,
    "totalBins": 40
  },
  "fees": {
    "dailyFees": 0.753,
    "cumulativeFees": 0.7707,
    "feeCurrency": "USD"
  },
  "efficiency": 33,
  "hero": {
    "positionUsd": 46.21,
    "dailyFees": 0.753,
    "efficiency": 33,
    "efficiencyZone": "Outer",
    "shape": "Bid-Ask",
    "rangeStatus": "In Range",
    "currentPrice": 6.74,
    "rangeMin": 6.6518,
    "rangeMax": 6.9162,
    "milestoneNext": "Scout",
    "milestoneTarget": 5,
    "milestoneProgress": 15
  },
  "marketIntel": {
    "avaxPrice": 6.74,
    "change24h": -2.08,
    "volume24h": 1902892.54,
    "tvl": 373612.89,
    "trend": "bearish",
    "news": [
      {
        "headline": "AVAX down 2.08% in 24h",
        "impact": "bearish",
        "relevance": "high"
      },
      {
        "headline": "LFJ AVAX/USDC pool volume: $1902.9K",
        "impact": "neutral",
        "relevance": "medium"
      }
    ]
  },
  "strategyAdvisor": {
    "efficiency": 33,
    "efficiencyZone": "Outer",
    "recommendedAction": "Hold",
    "dcaType": "Micro-DCA",
    "dcaDetails": "Micro DCA — price in range",
    "rebalanceTrigger": "Price exits $6.65-$6.92 range",
    "compoundThreshold": 50,
    "cumulativeFees": 0.7707,
    "nextCompound": "$49.23 away from first compound",
    "riskLevel": "High",
    "riskNote": "Price at $6.74, 33% efficiency",
    "shape": "Bid-Ask"
  },
  "milestones": {
    "Scout": 5,
    "Raider": 20,
    "Warlord": 50,
    "Sovereign": 100
  },
  "feeMilestones": {
    "currentDailyFees": 0.753,
    "cumulativeFees": 0.7707,
    "positionUsd": 46.21,
    "daysActive": 1,
    "nextMilestone": "Scout",
    "nextTarget": 5,
    "progress": 15,
    "tiers": [
      {
        "tier": 1,
        "icon": "🔭",
        "label": "Scout",
        "target": 5,
        "unlocks": "Entry strategies (CURVE)",
        "achieved": false
      },
      {
        "tier": 2,
        "icon": "⚔️",
        "label": "Raider",
        "target": 20,
        "unlocks": "SPOT + BIDIRECTIONAL shapes",
        "achieved": false
      },
      {
        "tier": 3,
        "icon": "👑",
        "label": "Warlord",
        "target": 50,
        "unlocks": "Multi-pool positions",
        "achieved": false
      },
      {
        "tier": 4,
        "icon": "🏰",
        "label": "Sovereign",
        "target": 100,
        "unlocks": "Custom strategy creation + mentorship",
        "achieved": false
      }
    ]
  },
  "curveData": {
    "currentPrice": 6.74,
    "rangeMin": 6.6518,
    "rangeMax": 6.9162,
    "bins": [
      {
        "price": 6.6518,
        "depth": 1,
        "id": 8362859
      },
      {
        "price": 6.6584,
        "depth": 0.9565214398370447,
        "id": 8362860
      },
      {
        "price": 6.6651,
        "depth": 0.9130433099074957,
        "id": 8362861
      },
      {
        "price": 6.6718,
        "depth": 0.8695651800104991,
        "id": 8362862
      },
      {
        "price": 6.6784,
        "depth": 0.8260870500853609,
        "id": 8362863
      },
      {
        "price": 6.6851,
        "depth": 0.7826084899300765,
        "id": 8362864
      },
      {
        "price": 6.6918,
        "depth": 0.7391303600141541,
        "id": 8362865
      },
      {
        "price": 6.6985,
        "depth": 0.6956522300577771,
        "id": 8362866
      },
      {
        "price": 6.7052,
        "depth": 0.6521736699065842,
        "id": 8362867
      },
      {
        "price": 6.7119,
        "depth": 0.6100293803391328,
        "id": 8362868
      },
      {
        "price": 6.7186,
        "depth": 0.5681671020794816,
        "id": 8362869
      },
      {
        "price": 6.7253,
        "depth": 0.5254383650135308,
        "id": 8362870
      },
      {
        "price": 6.7321,
        "depth": 0.485302730192363,
        "id": 8362871
      },
      {
        "price": 6.7388,
        "depth": 0.43954108696924366,
        "id": 8362872
      },
      {
        "price": 6.7455,
        "depth": 0.39530611888213224,
        "id": 8362873
      },
      {
        "price": 6.7523,
        "depth": 0.3504103978915227,
        "id": 8362874
      },
      {
        "price": 6.759,
        "depth": 0.3064942326104081,
        "id": 8362875
      },
      {
        "price": 6.7658,
        "depth": 0.2624297151667625,
        "id": 8362876
      },
      {
        "price": 6.7726,
        "depth": 0.21836261284841296,
        "id": 8362877
      },
      {
        "price": 6.7793,
        "depth": 0.17574063287549738,
        "id": 8362878
      },
      {
        "price": 6.7861,
        "depth": 0.1318073992405756,
        "id": 8362879
      },
      {
        "price": 6.7929,
        "depth": 0.08802382214525951,
        "id": 8362880
      },
      {
        "price": 6.7997,
        "depth": 0.045252054561024366,
        "id": 8362881
      },
      {
        "price": 6.8065,
        "depth": 0.0906819519156873,
        "id": 8362882
      },
      {
        "price": 6.8133,
        "depth": 0.13662446712605358,
        "id": 8362883
      },
      {
        "price": 6.8201,
        "depth": 0.18381428144189746,
        "id": 8362884
      },
      {
        "price": 6.8269,
        "depth": 0.22835304112188237,
        "id": 8362885
      },
      {
        "price": 6.8337,
        "depth": 0.27579340826419313,
        "id": 8362886
      },
      {
        "price": 6.8406,
        "depth": 0.32343354983341144,
        "id": 8362887
      },
      {
        "price": 6.8474,
        "depth": 0.3710199289829453,
        "id": 8362888
      },
      {
        "price": 6.8543,
        "depth": 0.4173478419864086,
        "id": 8362889
      },
      {
        "price": 6.8611,
        "depth": 0.4653298935190996,
        "id": 8362890
      },
      {
        "price": 6.868,
        "depth": 0.5084110717736884,
        "id": 8362891
      },
      {
        "price": 6.8749,
        "depth": 0.558439939029528,
        "id": 8362892
      },
      {
        "price": 6.8817,
        "depth": 0.6062760862238148,
        "id": 8362893
      },
      {
        "price": 6.8886,
        "depth": 0.6544844495448174,
        "id": 8362894
      },
      {
        "price": 6.8955,
        "depth": 0.6956923152401024,
        "id": 8362895
      },
      {
        "price": 6.9024,
        "depth": 0.7352344364160197,
        "id": 8362896
      },
      {
        "price": 6.9093,
        "depth": 0.7738189520448474,
        "id": 8362897
      },
      {
        "price": 6.9162,
        "depth": 0.817668903318841,
        "id": 8362898
      }
    ]
  },
  "walletBalances": {
    "avax": 0.0965898362653247,
    "wavax": 6.06671055059e-7,
    "usdc": 0.000012,
    "liquidUsd": 0.65
  },
  "supportResistance": {
    "currentPrice": 6.74,
    "levels": [
      {
        "price": 6.92,
        "type": "resistance",
        "strength": "strong",
        "label": "Range High",
        "note": "Current position top"
      },
      {
        "price": 6.97,
        "type": "resistance",
        "strength": "weak",
        "label": "Minor Resistance",
        "note": "Local high"
      },
      {
        "price": 6.65,
        "type": "support",
        "strength": "strong",
        "label": "Range Low",
        "note": "Current position bottom"
      },
      {
        "price": 6.6,
        "type": "support",
        "strength": "weak",
        "label": "Minor Support",
        "note": "Local low"
      }
    ],
    "shapeRecommendation": {
      "shape": "Bid-Ask",
      "reason": "Price at $6.74, within $6.65-$6.92 range.",
      "optimalRange": [
        6.65,
        6.92
      ]
    },
    "proximityAlert": "Price 33% into range"
  },
  "rebalanceSuggestions": {
    "efficiency": 33,
    "price": 6.74,
    "rangeMin": 6.6518,
    "rangeMax": 6.9162,
    "volatility": 2.08,
    "trend": "bearish",
    "suggestions": [
      {
        "icon": "⚠️",
        "title": "Price Near Edge",
        "description": "Price is near the edge of your range (33% efficiency). Consider narrowing or recentering.",
        "priority": "medium",
        "impact": "Moderate",
        "action": "Review Range"
      },
      {
        "icon": "📉",
        "title": "Bearish Pressure",
        "description": "AVAX is down 24h. Widen range or shift lower to avoid going out of range.",
        "priority": "low",
        "impact": "Risk",
        "action": "Adjust Down"
      }
    ]
  },
  "transactions": [
    {
      "date": "2026-06-17",
      "type": "Snapshot",
      "token": "AVAX/USDC",
      "amount": "3.2483 WAVAX + 24.31 USDC",
      "usd": "46.21",
      "status": "In Range"
    },
    {
      "date": "2026-06-16",
      "type": "Snapshot",
      "token": "AVAX/USDC",
      "amount": "1.4205 WAVAX + 36.12 USDC",
      "usd": "45.90",
      "status": "In Range"
    }
  ]
}