{
  "lastUpdated": "2026-06-20T12:40:23.481Z",
  "pool": "AVAX/USDC",
  "chain": "Avalanche",
  "dex": "LFJ",
  "currentPrice": 6.15,
  "priceChange24h": 1.51,
  "volume24h": 1351595.74,
  "liquidity": 351357.03,
  "lpPosition": {
    "pair": "AVAX/USDC",
    "feeTier": "10bps",
    "shape": "curve",
    "displayShape": "Curve",
    "currentPrice": 6.15,
    "rangeMin": 6.0796,
    "rangeMax": 6.2521,
    "avaxAmount": 3.80353,
    "usdcAmount": 19.445183,
    "totalValue": 42.84,
    "totalValueUSD": 42.84,
    "activeBin": 8362782,
    "binStep": 10,
    "totalBins": 29
  },
  "fees": {
    "dailyFees": 0.527,
    "cumulativeFees": 1.1405,
    "feeCurrency": "USD"
  },
  "efficiency": 82,
  "hero": {
    "positionUsd": 42.84,
    "dailyFees": 0.527,
    "efficiency": 82,
    "efficiencyZone": "Center",
    "shape": "Curve",
    "rangeStatus": "In Range",
    "currentPrice": 6.15,
    "rangeMin": 6.0796,
    "rangeMax": 6.2521,
    "milestoneNext": "Scout",
    "milestoneTarget": 5,
    "milestoneProgress": 11
  },
  "marketIntel": {
    "avaxPrice": 6.15,
    "change24h": 1.51,
    "volume24h": 1351595.74,
    "tvl": 351357.03,
    "trend": "neutral",
    "news": [
      {
        "headline": "AVAX up 1.51% in 24h",
        "impact": "bullish",
        "relevance": "high"
      },
      {
        "headline": "LFJ AVAX/USDC pool volume: $1351.6K",
        "impact": "neutral",
        "relevance": "medium"
      }
    ]
  },
  "strategyAdvisor": {
    "efficiency": 82,
    "efficiencyZone": "Center",
    "recommendedAction": "Hold",
    "dcaType": "Full DCA",
    "dcaDetails": "Full DCA — price in range",
    "rebalanceTrigger": "Price exits $6.08-$6.25 range",
    "compoundThreshold": 50,
    "cumulativeFees": 1.1405,
    "nextCompound": "$48.86 away from first compound",
    "riskLevel": "Low",
    "riskNote": "Price at $6.15, 82% efficiency",
    "shape": "Curve"
  },
  "milestones": {
    "Scout": 5,
    "Raider": 20,
    "Warlord": 50,
    "Sovereign": 100
  },
  "feeMilestones": {
    "currentDailyFees": 0.527,
    "cumulativeFees": 1.1405,
    "positionUsd": 42.84,
    "daysActive": 1,
    "nextMilestone": "Scout",
    "nextTarget": 5,
    "progress": 11,
    "tiers": [
      {
        "tier": 1,
        "icon": "🔭",
        "label": "Scout",
        "target": 5,
        "unlocks": "Entry strategies (CURVE)",
        "achieved": false
      },
      {
        "tier": 2,
        "icon": "⚔️",
        "label": "Raider",
        "target": 20,
        "unlocks": "SPOT + BIDIRECTIONAL shapes",
        "achieved": false
      },
      {
        "tier": 3,
        "icon": "👑",
        "label": "Warlord",
        "target": 50,
        "unlocks": "Multi-pool positions",
        "achieved": false
      },
      {
        "tier": 4,
        "icon": "🏰",
        "label": "Sovereign",
        "target": 100,
        "unlocks": "Custom strategy creation + mentorship",
        "achieved": false
      }
    ]
  },
  "curveData": {
    "currentPrice": 6.15,
    "rangeMin": 6.0796,
    "rangeMax": 6.2521,
    "bins": [
      {
        "price": 6.0796,
        "depth": 0.07367181534641157,
        "id": 8362769
      },
      {
        "price": 6.0856,
        "depth": 0.10323018247483885,
        "id": 8362770
      },
      {
        "price": 6.0917,
        "depth": 0.1413214727036443,
        "id": 8362771
      },
      {
        "price": 6.0978,
        "depth": 0.18901919819106175,
        "id": 8362772
      },
      {
        "price": 6.1039,
        "depth": 0.24700145624262543,
        "id": 8362773
      },
      {
        "price": 6.11,
        "depth": 0.31534760229389,
        "id": 8362774
      },
      {
        "price": 6.1161,
        "depth": 0.3933468432375477,
        "id": 8362775
      },
      {
        "price": 6.1222,
        "depth": 0.4793555338719371,
        "id": 8362776
      },
      {
        "price": 6.1284,
        "depth": 0.57073757517906,
        "id": 8362777
      },
      {
        "price": 6.1345,
        "depth": 0.663912776864705,
        "id": 8362778
      },
      {
        "price": 6.1406,
        "depth": 0.7545394089183499,
        "id": 8362779
      },
      {
        "price": 6.1468,
        "depth": 0.838656679017251,
        "id": 8362780
      },
      {
        "price": 6.1529,
        "depth": 0.9105550373359371,
        "id": 8362781
      },
      {
        "price": 6.1591,
        "depth": 0.9646755124681832,
        "id": 8362782
      },
      {
        "price": 6.1652,
        "depth": 1,
        "id": 8362783
      },
      {
        "price": 6.1714,
        "depth": 0.9645823540655555,
        "id": 8362784
      },
      {
        "price": 6.1776,
        "depth": 0.906794152189464,
        "id": 8362785
      },
      {
        "price": 6.1837,
        "depth": 0.864858430276315,
        "id": 8362786
      },
      {
        "price": 6.1899,
        "depth": 0.8004060672104925,
        "id": 8362787
      },
      {
        "price": 6.1961,
        "depth": 0.7181729945858932,
        "id": 8362788
      },
      {
        "price": 6.2023,
        "depth": 0.6247351881425839,
        "id": 8362789
      },
      {
        "price": 6.2085,
        "depth": 0.5268792141734034,
        "id": 8362790
      },
      {
        "price": 6.2147,
        "depth": 0.4307986786560997,
        "id": 8362791
      },
      {
        "price": 6.2209,
        "depth": 0.3414961870971249,
        "id": 8362792
      },
      {
        "price": 6.2272,
        "depth": 0.2624493823358442,
        "id": 8362793
      },
      {
        "price": 6.2334,
        "depth": 0.1955480324353489,
        "id": 8362794
      },
      {
        "price": 6.2396,
        "depth": 0.1412568591820254,
        "id": 8362795
      },
      {
        "price": 6.2459,
        "depth": 0.09892677244416533,
        "id": 8362796
      },
      {
        "price": 6.2521,
        "depth": 0.06716860585908294,
        "id": 8362797
      }
    ]
  },
  "walletBalances": {
    "avax": 0.09746053057497317,
    "wavax": 6.06671055207e-7,
    "usdc": 0.000007,
    "liquidUsd": 0.6
  },
  "supportResistance": {
    "currentPrice": 6.15,
    "levels": [
      {
        "price": 6.25,
        "type": "resistance",
        "strength": "strong",
        "label": "Range High",
        "note": "Current position top"
      },
      {
        "price": 6.29,
        "type": "resistance",
        "strength": "weak",
        "label": "Minor Resistance",
        "note": "Local high"
      },
      {
        "price": 6.08,
        "type": "support",
        "strength": "strong",
        "label": "Range Low",
        "note": "Current position bottom"
      },
      {
        "price": 6.05,
        "type": "support",
        "strength": "weak",
        "label": "Minor Support",
        "note": "Local low"
      }
    ],
    "shapeRecommendation": {
      "shape": "Curve",
      "reason": "Price at $6.15, within $6.08-$6.25 range.",
      "optimalRange": [
        6.08,
        6.25
      ]
    },
    "proximityAlert": "Price 41% into range"
  },
  "rebalanceSuggestions": {
    "efficiency": 82,
    "price": 6.15,
    "rangeMin": 6.0796,
    "rangeMax": 6.2521,
    "volatility": 1.51,
    "trend": "neutral",
    "suggestions": [
      {
        "icon": "✅",
        "title": "Position Healthy",
        "description": "Price is in range and efficiency is good. No action needed.",
        "priority": "low",
        "impact": "None",
        "action": null
      }
    ]
  },
  "transactions": [
    {
      "date": "2026-06-20",
      "type": "Snapshot",
      "token": "AVAX/USDC",
      "amount": "3.8035 WAVAX + 19.45 USDC",
      "usd": "42.84",
      "status": "In Range"
    },
    {
      "date": "2026-06-19",
      "type": "Snapshot",
      "token": "AVAX/USDC",
      "amount": "3.2695 WAVAX + 23.11 USDC",
      "usd": "42.37",
      "status": "In Range"
    },
    {
      "date": "2026-06-18",
      "type": "Snapshot",
      "token": "AVAX/USDC",
      "amount": "1.6018 WAVAX + 34.10 USDC",
      "usd": "44.18",
      "status": "In Range"
    }
  ]
}